ramba/__init__.py
ramba/_version.py
ramba/common.py
ramba/fileio.py
ramba/numa.py
ramba/numba_ext.py
ramba/ramba.py
ramba/ramba_queue.py
ramba/ramba_queue_mpi.py
ramba/ramba_queue_zmq.py
ramba/ramba_uuid.py
ramba/shardview.py
ramba/shardview_array.py
ramba/random/__init__.py
ramba/random/random.py
ramba/tests/__init__.py
ramba/tests/test_distributed_array.py
ramba/tests/test_groupby.py
ramba/tests/test_xarray.py
ramba-0.1.post157.dist-info/LICENSE
ramba-0.1.post157.dist-info/LICENSES.third_party
ramba-0.1.post157.dist-info/METADATA
ramba-0.1.post157.dist-info/WHEEL
ramba-0.1.post157.dist-info/top_level.txt
ramba-0.1.post157.dist-info/RECORD
