Metadata-Version: 2.1
Name: ramba
Version: 0.1.post157
Summary: Distributed Numpy-like arrays in Python
Home-page: https://github.com/Python-for-HPC/ramba
Author: Intel, Inc.
Author-email: todd.a.anderson@intel.com
License: BSD
Requires-Python: >=3.7
License-File: LICENSE
License-File: LICENSES.third_party
Requires-Dist: numba
Requires-Dist: ray
Requires-Dist: pyzmq
Requires-Dist: cloudpickle
Requires-Dist: numpy (<1.23)
Requires-Dist: psutil
Requires-Dist: six
Requires-Dist: setuptools
Requires-Dist: pickle5 ; python_version < "3.8"
